{
  "user_id": "user_024",
  "task": "I’m helping put together a simple weather project for class, and I want it to be more interesting than just a poster with facts. Can you suggest a good way to show how weather can change fast so it’s easy for kids to notice?",
  "prefs": [
    {
      "idx": 1,
      "dimension": "formality_preference",
      "short": "Likes simple, friendly conversation",
      "explanation": "She seems best suited to a casual, approachable style rather than anything stiff or formal. As a 10-year-old student, she would likely respond better when help feels natural and easy to talk through."
    },
    {
      "idx": 2,
      "dimension": "verbosity_preference",
      "short": "Prefers short, manageable answers",
      "explanation": "She would likely do better with responses that are not too long at once. Since she is young, concise help that gets to the point is more usable than big blocks of text."
    },
    {
      "idx": 3,
      "dimension": "pacing_preference",
      "short": "Wants help in small steps",
      "explanation": "She likely benefits from one part at a time instead of being overwhelmed with many instructions together. Step-by-step pacing fits a student who is still learning and likes practical guidance."
    },
    {
      "idx": 4,
      "dimension": "tone_preference",
      "short": "Likes warm, encouraging help",
      "explanation": "Her kind and hopeful nature suggests she responds well to a friendly tone that feels supportive. She probably does not want harsh or cold wording, especially when asking for help with school or everyday tasks."
    },
    {
      "idx": 5,
      "dimension": "format_preference",
      "short": "Does best with clear, simple formatting",
      "explanation": "She likely understands help better when it is organized clearly, such as with short bullets or easy lists. That kind of format would fit her age and her practical style of learning from examples and observations."
    }
  ],
  "turns": [
    {
      "turn": 1,
      "agent_response": "Yes — a good kid-friendly way is to show **“before and after” weather**.\n\n### Simple project idea\nMake a small chart or drawing with:\n- **Morning sky**\n- **Afternoon sky**\n- **What changed**\n\n### What to show\nPick 3 things that can change fast:\n- **clouds** — white to dark gray\n- **wind** — calm to windy\n- **light** — bright to dim\n- **rain** — dry to wet\n\n### Easy example\n- **Before:** blue sky, calm wind, dry ground  \n- **After:** dark clouds, stronger wind, puddles\n\n### Another fun way\nUse a **flip book** or **two side-by-side pictures**:\n- one page = “looks fine”\n- next page = “storm coming”\n\n### Simple sentence kids can write\n“Weather can change fast when clouds get darker and wind gets stronger.”\n\nIf you want, I can make you a **super short class project template** with boxes to fill in.",
      "score": 5.0,
      "summary": "mean=5.00 over 5/5 prefs (na=0); dist={1:0, 2:0, 3:0, 4:0, 5:5}",
      "per_pref": [
        {
          "idx": 1,
          "score": 5,
          "reason": "Uses a simple, friendly style like \"Yes — a good kid-friendly way\" and \"If you want, I can make you...\" rather than sounding stiff or formal."
        },
        {
          "idx": 2,
          "score": 5,
          "reason": "Keeps it short and manageable with concise sections and brief examples instead of a long explanation."
        },
        {
          "idx": 3,
          "score": 5,
          "reason": "Gives small steps and one idea at a time, such as \"Simple project idea,\" \"What to show,\" and \"Another fun way.\""
        },
        {
          "idx": 4,
          "score": 5,
          "reason": "Warm and encouraging tone throughout, e.g. \"good kid-friendly way,\" \"easy,\" and offering extra help at the end."
        },
        {
          "idx": 5,
          "score": 5,
          "reason": "Uses clear formatting with headings, bullets, and short lists, which makes the advice easy to follow."
        }
      ]
    },
    {
      "turn": 2,
      "agent_response": "Absolutely — a simple **3-part project** would make that feel much more real.\n\n### Tiny weather project: 3 parts\n1. **Start**\n   - Draw or show what the weather looked like first.\n   - Example: blue sky, calm wind, dry ground.\n\n2. **Change**\n   - Show the thing that started changing.\n   - Example: clouds got darker, wind picked up, sky looked dimmer.\n\n3. **End**\n   - Show what it became.\n   - Example: rain started, puddles formed, everyone went inside.\n\n### Easy way to make it hands-on\nUse:\n- **3 boxes on a poster**\n- or **3 index cards**\n- or **3 drawings in a row**\n\n### What kids can point to\nYou can label the change with arrows:\n- **clouds → darker**\n- **wind → stronger**\n- **ground → wet**\n\n### Tiny example sentence\n“First it looked calm, then the clouds got dark, and then it started raining.”\n\nIf you want, I can turn this into a **kid-sized fill-in template** with just 3 blanks.",
      "score": 5.0,
      "summary": "mean=5.00 over 5/5 prefs (na=0); dist={1:0, 2:0, 3:0, 4:0, 5:5}",
      "per_pref": [
        {
          "idx": 1,
          "score": 5,
          "reason": "Uses a casual, friendly style like \"Absolutely\" and \"If you want,\" which feels approachable rather than stiff or formal."
        },
        {
          "idx": 2,
          "score": 5,
          "reason": "Keeps it short and manageable with a compact 3-part structure and brief examples instead of a long explanation."
        },
        {
          "idx": 3,
          "score": 5,
          "reason": "Breaks the idea into small steps: \"Start,\" \"Change,\" \"End,\" which is clear step-by-step pacing."
        },
        {
          "idx": 4,
          "score": 5,
          "reason": "Warm and encouraging tone throughout, e.g. \"Absolutely\" and \"If you want, I can turn this into a kid-sized fill-in template,\" which feels supportive."
        },
        {
          "idx": 5,
          "score": 5,
          "reason": "Uses clear, simple formatting with headings, numbered steps, and bullet points, making it easy to follow."
        }
      ]
    }
  ]
}