{
  "user_id": "user_022",
  "task": "I need to send a short follow-up to a vendor about a quote that doesn’t match the spec we discussed, and I want to make sure I cover the key points clearly. Can you help me draft a message that gets the issue across without adding extra detail?",
  "ground_truth": null,
  "end_reason": "satisfied",
  "final_preference_score": 4.6,
  "final_gt_correct": null,
  "turns": [
    {
      "turn": 1,
      "agent_response": "Absolutely — here’s a short, clear version:\n\nHi [Vendor Name],\n\nI reviewed the quote, and it doesn’t match the spec we discussed. Can you please confirm the exact spec being quoted and update it if needed?\n\nOnce that’s corrected, please resend the revised quote.\n\nThanks,  \n[Your Name]\n\nIf you want, I can make it even firmer or more casual.",
      "user_simulator": {
        "feedback_type": "satisfied",
        "text": "That works. Short, clear, gets the point across without a bunch of extra wording.",
        "is_done": true
      },
      "preference_evaluator": {
        "score": 4.6
      },
      "gt_correct": null
    }
  ]
}