{
  "user_id": "user_001",
  "task": "Can you help me map out a simple school-night plan for tomorrow? I’ve got homework, dinner, and a little reading to fit in, and I want to make sure I don’t forget anything important.",
  "ground_truth": null,
  "end_reason": "satisfied",
  "final_preference_score": 5.0,
  "final_gt_correct": null,
  "turns": [
    {
      "turn": 1,
      "agent_response": "Absolutely — here’s a simple school-night plan you can follow tomorrow:\n\n### School-Night Plan\n- **Get home / snack / rest:** 20–30 min\n- **Homework:** 45–60 min\n- **Dinner:** 30 min\n- **Reading:** 15–20 min\n- **Pack up / check tomorrow:** 10 min\n- **Free time / get ready for bed:** whatever is left\n\n### Easy order to follow\n1. Get home and take a short break  \n2. Do homework  \n3. Eat dinner  \n4. Read a little  \n5. Pack up for tomorrow  \n6. Relax and get ready for bed\n\n### Quick checklist\n- [ ] Homework done  \n- [ ] Dinner eaten  \n- [ ] Reading finished  \n- [ ] Backpack ready  \n- [ ] Tomorrow checked  \n\nIf you want, I can turn this into a **specific schedule with exact times** too.",
      "user_simulator": {
        "feedback_type": "followup",
        "text": "Pretty good, but I want exact times. Just the simple schedule, like what time to start homework, dinner, reading, and packing. Keep it tight.",
        "is_done": false
      },
      "preference_evaluator": {
        "score": 5.0
      },
      "gt_correct": null
    },
    {
      "turn": 2,
      "agent_response": "Sure — here’s a tight schedule with exact times:\n\n### Tomorrow’s School-Night Plan\n- **3:30–3:50** get home, snack, rest  \n- **3:50–4:50** homework  \n- **4:50–5:20** dinner  \n- **5:20–5:40** reading  \n- **5:40–5:50** pack up / check tomorrow  \n- **5:50 onward** free time / get ready for bed  \n\n### Quick checklist\n- [ ] Homework  \n- [ ] Dinner  \n- [ ] Reading  \n- [ ] Backpack ready  \n- [ ] Tomorrow checked  \n\nIf you want, I can make this into a **super short screenshot-style checklist** too.",
      "user_simulator": {
        "feedback_type": "satisfied",
        "text": "Yeah, that works. Simple and clear.",
        "is_done": true
      },
      "preference_evaluator": {
        "score": 5.0
      },
      "gt_correct": null
    }
  ]
}