{
  "user_id": "user_023",
  "task": "I’m trying to decide whether to answer a message or just leave it alone, but I don’t want to overcomplicate it. Can you help me draft a reply that’s brief and gets the point across?",
  "ground_truth": null,
  "end_reason": "satisfied",
  "final_preference_score": 4.6,
  "final_gt_correct": null,
  "turns": [
    {
      "turn": 1,
      "agent_response": "Yep — paste the message and I’ll help you make it **short, clear, and not overthought**.\n\nIf you want, I can format it as:\n- **reply**\n- **leave it alone**\n- **maybe reply later**\n\nOr I can give you 2–3 quick reply options depending on the vibe.",
      "user_simulator": {
        "feedback_type": "add_context",
        "text": "Yeah, here’s the message: “hey, you good? you’ve been quiet.”\n\nI don’t want to sound extra. Just something short. Maybe like “yeah, just busy” or “I’m fine, just got stuff going on.”",
        "is_done": false
      },
      "preference_evaluator": {
        "score": 4.4
      },
      "gt_correct": null
    },
    {
      "turn": 2,
      "agent_response": "Yeah — keep it simple.\n\nBest short options:\n- **“Yeah, just been busy.”**\n- **“I’m good, just got stuff going on.”**\n- **“Yeah, all good — just quiet lately.”**\n\nIf you want the least extra one, I’d use:\n**“Yeah, just been busy.”**\n\nIf you want, I can also give you:\n- a **slightly warmer** version\n- a **more distant** version\n- a **don’t want to keep talking** version",
      "user_simulator": {
        "feedback_type": "satisfied",
        "text": "Yeah, that works. \"Yeah, just been busy.\" is fine. short, not weird.",
        "is_done": true
      },
      "preference_evaluator": {
        "score": 4.8
      },
      "gt_correct": null
    }
  ]
}