{
  "user_id": "user_025",
  "task": "I’m dealing with a vendor who says the order needs to be adjusted after delivery because of a small issue. Can you help me draft a short response that asks for the relevant paperwork and keeps the conversation focused on the documented order details?",
  "ground_truth": null,
  "end_reason": "satisfied",
  "final_preference_score": 4.4,
  "final_gt_correct": null,
  "turns": [
    {
      "turn": 1,
      "agent_response": "Sure — here’s a short, firm reply you can use:\n\n> Please send over the relevant paperwork showing the requested adjustment, including the original order details, delivery record, and any supporting documentation for the issue you’re referencing. For now, let’s keep this limited to the documented order terms and any written changes to them.\n\nIf you want, I can also make it:\n- a little softer\n- more firm/professional\n- or tailored for email/text to the vendor",
      "user_simulator": {
        "feedback_type": "satisfied",
        "text": "Yeah, that works. Short, clean, and it keeps them on the paperwork instead of hand-waving around it.",
        "is_done": true
      },
      "preference_evaluator": {
        "score": 4.4
      },
      "gt_correct": null
    }
  ]
}